pypst/__init__.py
pypst/pst_learn.py
pypst/pst_to_pfa.py
pypst/test_example_trees.py
pypst/test_pst_learn.py
pypst/test_transition_mat.py
pypst/transition_mat.py
pypst/wrapper.py
psuffix_trees-1.0.0.dist-info/LICENSE
psuffix_trees-1.0.0.dist-info/METADATA
psuffix_trees-1.0.0.dist-info/WHEEL
psuffix_trees-1.0.0.dist-info/top_level.txt
psuffix_trees-1.0.0.dist-info/RECORD
