Metadata-Version: 2.1
Name: psuffix-trees
Version: 1.0.0
Summary: A Python port of the Matlab probabilistic suffix trees and automata library by Markowitz
Author-email: Russell McLoughlin <russ.mcl@gmail.com>
License: MIT License
Project-URL: Homepage, https://github.com/rmcl/psuffix-trees
Keywords: pst,probabilistic suffix trees,python
Classifier: Programming Language :: Python :: 3
Classifier: License :: OSI Approved :: MIT License
Classifier: Operating System :: OS Independent
Requires-Python: >=3.7
License-File: LICENSE
Requires-Dist: numpy>=1.21
